cl2csv
