Metadata-Version: 1.0
Name: django-cl2csv
Version: 0.11
Summary: Export what you see in the Django admin list view.
Home-page: https://github.com/protonpopsicle/django-cl2csv
Author: Scott Meisburger
Author-email: smeisburger@gmail.com
License: GPLv3
Keywords: django csv export
Platform: UNKNOWN
